[
  {
    "id": 0,
    "title": "Notebook",
    "price": 2000,
    "description": "It's notebook",
    "quantity": 0
  },
  {
    "id": 1,
    "title": "Mouse",
    "price": 20,
    "description": "It's mouse",
    "quantity": 0
  },
  {
    "id": 2,
    "title": "Keyboard",
    "price": 200,
    "description": "It's keyboard",
    "quantity": 0
  },
  {
    "id": 3,
    "title": "Gamepad",
    "price": 50,
    "description": "It's gamepad",
    "quantity": 0
  }
]
